Metadata-Version: 2.2
Name: faketaxi
Version: 6.9
Summary: This package can be used to convert Excel invoices to PDF invoices.
Home-page: https://skycowboy.com
Author: Sky Cowboy
Author-email: skycowboy@noreply.com
License: MIT
Keywords: taxi,fake taxi,fake
Classifier: Development Status :: 3 - Alpha
Classifier: Intended Audience :: Developers
Classifier: Topic :: Software Development :: Build Tools
Classifier: License :: OSI Approved :: MIT License
Classifier: Programming Language :: Python :: 3.8
Classifier: Programming Language :: Python :: 3.9
Classifier: Programming Language :: Python :: 3.10
Classifier: Programming Language :: Python :: 3.11
Requires-Dist: pandas
Requires-Dist: fpdf
Requires-Dist: openpyxl
Dynamic: author
Dynamic: author-email
Dynamic: classifier
Dynamic: home-page
Dynamic: keywords
Dynamic: license
Dynamic: requires-dist
Dynamic: summary
